faker_marketdata/MarketDataProvider.py
faker_marketdata/__init__.py
tests/__init__.py
tests/test_marketdata.py
faker_marketdata-0.4.dist-info/LICENSE
faker_marketdata-0.4.dist-info/METADATA
faker_marketdata-0.4.dist-info/WHEEL
faker_marketdata-0.4.dist-info/top_level.txt
faker_marketdata-0.4.dist-info/RECORD
